HISTORY.rst
LICENSE
MANIFEST.in
README.rst
setup.py
django_notifyme_onsite.egg-info/PKG-INFO
django_notifyme_onsite.egg-info/SOURCES.txt
django_notifyme_onsite.egg-info/dependency_links.txt
django_notifyme_onsite.egg-info/not-zip-safe
django_notifyme_onsite.egg-info/top_level.txt
notifyme_onsite/__init__.py
notifyme_onsite/admin.py
notifyme_onsite/context_processors.py
notifyme_onsite/delivery_backends.py
notifyme_onsite/models.py
notifyme_onsite/settings.py
notifyme_onsite/urls.py
notifyme_onsite/views.py
notifyme_onsite/migrations/0001_initial.py
notifyme_onsite/migrations/__init__.py
notifyme_onsite/templates/notifyme/notification_types/generic/onsite/sticky.html