Metadata-Version: 1.0
Name: django-notifyme-onsite
Version: 0.0.2a1
Summary: An on site delivery backend for django-notifyme
Home-page: http://github.com/stefanfoulis/django-notifyme-onsite
Author: Stefan Foulis
Author-email: stefan.foulis@gmail.com
License: BSD
Platform: OS Independent
Classifier: Development Status :: 3 - Alpha
Classifier: Framework :: Django
Classifier: Intended Audience :: Developers
Classifier: License :: OSI Approved :: BSD License
Classifier: Operating System :: OS Independent
Classifier: Programming Language :: Python
Classifier: Topic :: Internet :: WWW/HTTP
